{
    "patient_id": "DUKE_009",
    "clinical_data": {
        "age": 56,
        "menopausal_status": "post",
        "breast_density": ""
    },
    "primary_lesion": {
        "pcr": 1,
        "tumor_subtype": "triple_negative",
        "breast_coordinates": {
            "x_min": 1,
            "x_max": 154,
            "y_min": 61,
            "y_max": 308,
            "z_min": 14,
            "z_max": 256
        }
    },
    "imaging_data": {
        "bilateral": true,
        "dataset": "DUKE",
        "site": "DUKE",
        "scanner_manufacturer": "GE",
        "scanner_model": "Signa HDxt",
        "field_strength": 3.0,
        "echo_time": 2.604,
        "repetition_time": 6.032
    }
}